gitlab_registry_usage_rest/__init__.py
gitlab_registry_usage_rest/__main__.py
gitlab_registry_usage_rest/_version.py
gitlab_registry_usage_rest/app.py
gitlab_registry_usage_rest/auth.py
gitlab_registry_usage_rest/cache.py
gitlab_registry_usage_rest/config.py
gitlab_registry_usage_rest/resources.py
gitlab_registry_usage_rest-0.3.3.dist-info/LICENSE
gitlab_registry_usage_rest-0.3.3.dist-info/METADATA
gitlab_registry_usage_rest-0.3.3.dist-info/WHEEL
gitlab_registry_usage_rest-0.3.3.dist-info/entry_points.txt
gitlab_registry_usage_rest-0.3.3.dist-info/top_level.txt
gitlab_registry_usage_rest-0.3.3.dist-info/RECORD
